{"Personal": {"Male": {"Common": ["Andr\u00e1s", "Attila", "Csaba", "Ferenc", "G\u00e1bor", "Gy\u00f6rgy", "Gyula", "Imre", "Istv\u00e1n", "J\u00e1nos", "J\u00f3zsef", "Lajos", "L\u00e1szl\u00f3", "Mih\u00e1ly", "P\u00e9ter", "S\u00e1ndor", "Tam\u00e1s", "Tibor", "Zolt\u00e1n", "Zsolt"], "Diminutive": {"Istv\u00e1n": ["Pista", "Pisti", "Pityu", "Pistika", "Pityuka"], "L\u00e1szl\u00f3": ["Laci", "Lacika", "Lack\u00f3", "Lala"], "J\u00f3zsef": ["J\u00f3ska", "J\u00f3zsi", "J\u00f3zsika", "J\u00f3ci", "J\u00f3ka"], "J\u00e1nos": ["Jani", "Jancsi", "Janika", "Jancsika"], "S\u00e1ndor": ["Sanyi", "Elek", "Dodi"]}, "Standard": ["\u00c1bel", "Adalbert", "\u00c1d\u00e1m", "\u00c1goston", "\u00c1kos", "Alajos", "Albert", "\u00c1lmos", "Ambrus", "Andr\u00e1s", "Antal", "\u00c1rp\u00e1d", "Atilla", "Attila", "Bal\u00e1zs", "B\u00e1lint", "Barnab\u00e1s", "B\u00e9la", "Bence", "Benedek", "Bern\u00e1t", "Bertalan", "Boldizs\u00e1r", "Csaba", "Cs\u00e1k", "Csongor", "D\u00e1niel", "D\u00e1vid", "Demeter", "D\u00e9nes", "Dezs\u00f4", "D\u00f6me", "D\u00f6m\u00f6t\u00f6r", "Ede", "Elek", "Elem\u00e9r", "Endre", "Ern\u00f6", "Ern\u00f4", "Ervin", "F\u00e1bi\u00e1n", "Farkas", "Ferenc", "Frigyes", "F\u00fcl\u00f6p", "G\u00e1bor", "G\u00e1briel", "G\u00e1sp\u00e1r", "Gell\u00e9rt", "Gergely", "Gerg\u00f4", "G\u00e9za", "Gottfrid", "Guszt\u00e1v", "Gy\u00f4z\u00f4", "Gy\u00f6rgy", "Gyula", "Henrik", "Ign\u00e1c", "Ignacz", "\u00cdll\u00e9s", "Imre", "Istv\u00e1n", "Izs\u00e1k", "Jakab", "J\u00e1kob", "J\u00e1nos", "Jen\u00f4", "Jer\u00e9mi\u00e1s", "J\u00f3zsef", "K\u00e1lm\u00e1n", "K\u00e1roly", "Kelemen", "Konr\u00e1d", "Korn\u00e9l", "Krist\u00f3f", "Kriszti\u00e1n", "Lajos", "L\u00e1szl\u00f3", "L\u00e1z\u00e1r", "Levente", "Lipot", "L\u00f3r\u00e1nd", "L\u00f3r\u00e1nt", "L\u00f6rinc", "Luk\u00e1cs", "M\u00e1rk", "Martin", "M\u00e1rton", "M\u00e1t\u00e9", "M\u00e1ty\u00e1s", "Menyh\u00e9rt", "Mih\u00e1ly", "Mikl\u00f3s", "M\u00f3zes", "N\u00e1ndor", "Norbert", "\u00d6d\u00f6n", "Orb\u00e1n", "Oszk\u00e1r", "Ott\u00f3", "P\u00e1l", "P\u00e9ter", "Rezs\u00f6", "Rich\u00e1rd", "Rick\u00e1rd", "Rik\u00e1rd", "R\u00f3bert", "Roland", "Rudolf", "Rudulf", "Salamon", "S\u00e1muel", "S\u00e1ndor", "Sebesty\u00e9n", "Simon", "Soma", "Szabolcs", "Szil\u00e1rd", "Szilveszter", "Taddeus", "T\u00e1d\u00e9", "T\u00e1dor", "Tam\u00e1s", "Tibor", "Tiborc", "Tivadar", "T\u00f3bi\u00e1s", "Valter", "Vencel", "Viktor", "Vilmos", "Vince", "Zakari\u00e1s", "Zolt\u00e1n", "Zsigmond", "Zsolt"]}, "Female": {"Common": ["\u00c1gnes", "Andrea", "Anna", "Edit", "Erika", "Erzs\u00e9bet", "Eszter", "\u00c9va", "Ildik\u00f3", "Ilona", "Ir\u00e9n", "Judit", "Julianna", "Katalin", "Krisztina", "Magdolna", "Margit", "M\u00e1ria", "Roz\u00e1lia", "Zsuzsanna"], "Diminutive": {"M\u00e1ria": ["Mara", "Mari", "Maris", "Marika", "Mariska", "Marica", "Manci", "Ria", "Rica", "Rika"], "Erzs\u00e9bet": ["Erzsi", "B\u00f6zsi", "Erzsike", "B\u00f6zsike"], "Ilona": ["Ilonka", "Ica", "Ilus", "Cilka", "Ilka", "Ili"], "Katalin": ["Kata", "Katinka", "Kat\u00f3", "Kata", "Kati", "Kato", "Katica", "Katika"], "\u00c9va": ["\u00c9vi", "Vica", "\u00c9vike"]}, "Standard": ["Ade", "Adrienn", "Ag\u00e1ta", "\u00c1gnes", "\u00c1gota", "Alexandra", "Aloizia", "Alojzia", "Am\u00e1lia", "Am\u00e9lia", "Andrea", "Anett", "Angyalka", "Anik\u00f3", "Anita", "Anito", "Anna", "Annam\u00e1ria", "Annina", "Aranka", "\u00c1rv\u00e1cska", "Barbara", "Be\u00e1ta", "Bernadett", "Borb\u00e1la", "Brigitta", "Cec\u00edlia", "Csilla", "Csillag", "D\u00f3ra", "Dorottya", "Edina", "Edit", "Elvira", "Emerencia", "Emese", "Emilia", "Emma", "Em\u00f4ke", "Enik\u00f4", "Erika", "Erzs\u00e9bet", "Eszter", "Eta", "Etel", "Etelka", "Eufrozina", "\u00c9va", "Franciska", "Fruzsina", "Gabriella", "Gizella", "Gunda", "Gy\u00f6ngyi", "Gy\u00f6ngyvet", "Gy\u00f6rgyi", "Hajnalka", "Hel\u00e9na", "Henriett", "Henrietta", "Ibolya", "Ida", "Ildik\u00f3", "Ilona", "Ir\u00e9n", "Irma", "J\u00e1cinta", "Jol\u00e1n", "J\u00f3zsa", "Judit", "J\u00falia", "Julianna", "Jusztina", "Kamilla", "Karolina", "Kata", "Katalin", "Katinka", "Kat\u00f3", "Kinga", "Kl\u00e1ra", "Krisztina", "L\u00e9na", "Lidia", "Lili\u00e1na", "Lilium", "Lina", "Luca", "Lucza", "Magda", "Magdal\u00e9na", "Magdolna", "Margar\u00e9ta", "Margit", "M\u00e1ria", "Marianna", "M\u00e1rta", "Matild", "Melinda", "M\u00f3nika", "Nikolett", "Nikoletta", "Nina", "N\u00f3ra", "Orsolya", "Ottilia", "Panna", "Patricia", "Piroska", "R\u00e9ka", "Ren\u00e1ta", "Rita", "R\u00f3za", "Roz\u00e1lia", "Rozanna", "R\u00f3zsa", "S\u00e1ra", "Sarolt", "Sarolta", "Szilvia", "Ter\u00e9z", "Ter\u00e9zia", "Tessza", "T\u00edmea", "T\u00fcnde", "Val\u00e9ria", "Verona", "Veronika", "Vikt\u00f3ria", "Vilma", "Viola", "Vir\u00e1g", "Zolt\u00e1na", "Zsanett", "Zs\u00f3fia", "Zsuzsa", "Zsuzsanna"]}}, "Family": {"Common": ["Balogh", "Farkas", "Fekete", "Horv\u00e1th", "Juh\u00e1sz", "Kiss", "Kov\u00e1cs", "Lakatos", "M\u00e9sz\u00e1ros", "Moln\u00e1r", "Nagy", "N\u00e9meth", "Ol\u00e1h", "Papp", "R\u00e1cz", "Simon", "Szab\u00f3", "Tak\u00e1cs", "T\u00f3th", "Varga"], "Standard": ["Abel", "Ambrus", "Antal", "Asztalos", "Ba\u00e1n", "Bakos", "Bal\u00e1zs", "B\u00e1lint", "Balla", "Balog", "Balogh", "Barab\u00e1s", "Barna", "Barta", "Bartha", "Beke", "Bene", "Benke", "Benk\u00f4", "Berecz", "Bir\u00f3", "Bodn\u00e1r", "Bodor", "Bogd\u00e1n", "Bogn\u00e1r", "Borb\u00e9ly", "Boros", "Budai", "Cs\u00e1sz\u00e1r", "Csik\u00f3s", "Csizmazia", "Csord\u00e1s", "Dank\u00f3", "D\u00e1vid", "De\u00e1k", "Demeter", "D\u00e9nes", "Dobos", "Domokos", "Domonkos", "D\u00f6m\u00f6t\u00f6r", "Dud\u00e1s", "Egyed", "Elek", "Erd\u00e9lyi", "Er\u00f4s", "F\u00e1bi\u00e1n", "Farag\u00f3", "Farkas", "Fazekas", "Feh\u00e9r", "Fekete", "Ferenc", "Ferenczy", "Fodor", "F\u00f6ldes", "Forg\u00e1ch", "F\u00fcl\u00f6p", "Ga\u00e1l", "G\u00e1bor", "G\u00e1l", "Galambos", "G\u00e1sp\u00e1r", "Gerencs\u00e9r", "Ger\u00f4", "Guly\u00e1s", "Gyulai", "Gyulay", "Hajdu", "Hal\u00e1sz", "Heged\u00fbs", "Herczeg", "Horv\u00e1th", "Husz\u00e1r", "Ill\u00e9s", "Imre", "Jakab", "J\u00e1nosi", "J\u00f3n\u00e1s", "J\u00f3zsef", "Juh\u00e1sz", "K\u00e1d\u00e1r", "Kardos", "K\u00e1rp\u00e1ti", "Kasz\u00e1s", "Katona", "Kelemen", "Kerekes", "Kir\u00e1ly", "Kis", "Kiss", "Kocsis", "Kolumb\u00e1n", "Kov\u00e1ch", "Kov\u00e1cs", "Kozma", "Krist\u00f3f", "Kults\u00e1r", "Kun", "Lakatos", "Lang", "L\u00e1szl\u00f3", "L\u00e1z\u00e1r", "Lengyel", "Lipt\u00e1k", "L\u00f6rinc", "L\u00f4rincz", "Lov\u00e1sz", "Luk\u00e1cs", "Madar\u00e1sz", "Magyar", "M\u00e1jer", "Major", "Makai", "Mark\u00f3", "M\u00e1rkus", "M\u00e1rton", "M\u00e1t\u00e9", "M\u00e1ty\u00e1s", "Mejer", "Mester", "M\u00e9sz\u00e1ros", "Mih\u00e1ly", "Mikl\u00f3s", "Moln\u00e1r", "Nagy", "Nemes", "N\u00e9meth", "Nov\u00e1k", "Ny\u00e1ri", "Nyerges", "Ol\u00e1h", "Orb\u00e1n", "Orosz", "Ors\u00f3s", "Pa\u00e1l", "P\u00e1l", "P\u00e1lffi", "P\u00e1link\u00e1s", "Pap", "Papp", "P\u00e1sztor", "Pataki", "P\u00e9ter", "Peth\u00f4", "Pint\u00e9r", "Polg\u00e1r", "Pusztay", "R\u00e1cz", "Rig\u00f3", "R\u00f3bert", "R\u00f3zsa", "Sa\u00e1gi", "Sa\u00e1ri", "S\u00e1ndor", "S\u00e1rk\u00f6zy", "Schmid", "Sebesty\u00e9n", "Simon", "Sipos", "Smit", "Solt\u00e9sz", "Somogyi", "Somos", "So\u00f3s", "S\u00f6r\u00f6ss", "S\u00f3s", "Szab\u00f3", "Szak\u00e1cs", "Szalai", "Sz\u00e1nt\u00f3", "Szathm\u00e1r", "Szegedi", "Sz\u00e9kely", "Szekeres", "Szil\u00e1gyi", "Szil\u00e1rd", "Sz\u00f4ke", "Sz\u00f6ll\u00f4s", "Sz\u00f4l\u00f4sy", "Sz\u00fbcs", "Taar", "Tak\u00e1cs", "Tak\u00e1ts", "Tam\u00e1s", "Tam\u00e1si", "Teleki", "T\u00e9li", "Thim\u00e1r", "Th\u00fari", "Torma", "T\u00f6r\u00f6k", "T\u00f3t", "T\u00f3th", "Ujv\u00e1ri", "Urb\u00e1n", "Vad\u00e1sz", "V\u00e1radi", "V\u00e1rady", "Varga", "Vargha", "Vass", "V\u00e9gh", "Veres", "Veress", "Vincze", "Vir\u00e1g", "Vir\u00e1gh", "V\u00f6r\u00f6s", "Zarka", "Zsink\u00f3"]}}