{"Mammals": {"Apes": ["bah", "beh", "boh", "bou", "buhn", "dah", "deh", "dih", "dou", "duhm", "eehm", "engah", "fou", "gah", "goh", "gohm", "guhn", "gwah", "hahn", "hou", "hwah", "huh", "jou", "juh", "kah", "keh", "keng", "kihm", "koh", "kong", "kreeh", "lah", "leh", "mah", "moh", "mohm", "muh", "nah", "nang", "neh", "nih", "noh", "nou", "nyoh", "ogh", "ououh", "roh", "sah", "sahm", "soh", "tah", "tahm", "toh", "ugh", "ungoh", "wah", "wuhn", "yah", "yoh", "zeh", "zih"], "Rats": ["heek", "histh", "hisvit", "ikit", "itch", "kree", "kwee", "kweev", "kwik", "neek", "neekit", "risik", "skee", "skiv", "skree", "skreek", "skreelk", "skrit", "skriv", "skwee", "sneek", "sneetch", "snik", "snikit", "snitch", "tchee", "tchirik", "weesk", "wisth", "wreek"], "Squirrels": ["cheekk", "chisk", "chreej", "eep", "kishik", "kreej", "kwirrik", "reep", "thrisk", "thriss"], "Dogs": ["ahou", "auw", "bow", "garoo", "growl", "gruff", "gruwl", "gurr", "haroou", "howgh", "hraugh", "hrahou", "hroou", "hruff", "hrusk", "kaiyah", "kurr", "laroou", "lhaoouh", "mutt", "roagh", "rriur", "ruff", "turr", "tyke", "whelp", "yahoou", "yaup", "yelp", "yiee", "yike", "yipe", "yowh", "yurr"], "Hyenas": ["bree", "breekah", "cachinn", "chikaha", "chree", "eehya", "eengi", "eheh", "ghee", "gheu", "ghnee", "ghree", "grigri", "hee", "hyee", "ihih", "jheer", "nyaha", "snreeh", "yeenh"], "Cats": ["hrish", "lirr", "liss", "lith", "lyau", "mau", "meer", "mew", "miah", "miau", "mihr", "mirhl", "mirr", "miu", "purrh", "saf", "sash", "serr", "sfee", "shah", "sharr", "shau", "shee", "sheer", "shim", "shurr", "siyth", "slif", "swish", "syau"], "Great Cats": ["gharrh", "gher", "grihm", "guarrh", "hleogh", "hrargh", "hroarr", "hrugh", "hruhr", "hurrh", "mhuurr", "parrn", "rhauhl", "rrowrr", "sabor", "shaor", "shargh", "sheethah", "taigh", "thurr"], "Horses": ["bree", "brhou", "bwihi", "gnayah", "hbraa", "hihn", "hnai", "hnee", "hneh", "hniwhi", "hnuy", "houyhn", "hree", "hrihih", "huhnim", "hwin", "ilhya", "maiah", "mhee", "mhneh", "mhwin", "nhiwin", "nyahey", "nyihih", "yhehi"], "Pigs": ["borcht", "borgha", "bucht", "ghreeh", "glutth", "gris", "gruh", "grunkh", "hirkh", "hirkha", "hoinh", "hoinkh", "hortha", "hrigh", "hrogh", "hrugh", "huerg", "hurnk", "huunh", "hween", "mucht", "oighn", "pachn", "pharho", "pohr", "shoat", "snorgh", "soueeh", "squeeh", "stoink", "tuskh"]}, "Arthropods": {"Crustaceans": ["blak", "blik", "bluk", "dikuk", "karch", "klakk", "klatt", "klik", "kluk", "klutt", "kack", "krak", "krik", "krub", "kruk", "krunk", "kulch", "kurch", "kwik", "kwuk", "schrab", "schrib", "schruk", "tchelk", "tchub", "tchuk", "tchulk", "tchunk", "tchutt", "tunch"], "Spiders": ["grik", "irrtt", "kilss", "kob", "krig", "krik", "krip", "ksob", "lob", "nik", "sich", "skik", "skrik", "snik", "stig", "spiv", "stich", "tchik", "tigik", "tik", "vib", "vip", "vob", "vrig", "wib", "wik", "wiv", "yib", "yig", "yob"], "Insects": ["chirr", "chirrk", "hrikk", "kikeek", "kirrik", "kizz", "kree", "kreex", "krekk", "krich", "kutch", "kzirr", "rikik", "rritz", "rrizzch", "shikirr", "skeetz", "skirr", "skisk", "skrak", "skrix", "skut", "strid", "strix", "tchik", "thrih", "thrix", "tzirch", "tzuk", "tzurr"]}, "Molluscs": {"Octopus": ["chlugh", "gohlb", "ghoch", "ghoth", "globb", "gloth", "grish", "grush", "mieuch", "mnelsh", "ogh", "ough", "phlem", "phlish", "shgor", "shob", "shog", "shulb", "slough", "squelgh", "yaagth", "yoch", "yog"], "Squid": ["ghagh", "ghuch", "glash", "glup", "glush", "guth", "lagh", "lulgh", "mauh", "mlulgh", "shluh", "shubb", "shug", "shul", "shum", "shuph", "slaugh", "sluagh", "slud", "sluph", "snulg", "ubb", "yug"], "Slugs": ["ghish", "gluh", "gluig", "glung", "milgh", "milsh", "phlid", "phlith", "shabh", "shelzh", "shig", "sith", "slaa", "slig", "slithe", "sphid", "squilg", "squirsh", "yilg", "yish", "yizh", "zilgh"]}, "Birds": {"Cries": ["breeer", "eew", "fee-bree", "fieew", "ih-ieee", "ih-iii", "kee-arr", "kee-yer", "keeerrr", "kraaa", "krr-eek", "krrreeep", "meeyah", "peerr", "peew", "skweeurr", "stree", "strii", "tzah-wiii", "weeeerr", "wha-whii"], "Croaks": ["awoik", "honk", "hroank", "kau-kau", "kaw", "kek", "kluck", "kraark", "krarr", "kroak", "kronk", "kwaa", "oikaa", "tcheck", "tseck", "tzuk", "whaw", "yenk"], "Tweets": ["dee-dee", "jeef", "kil-dee", "klee-ip", "klee-it", "klee-klee", "kleet", "li-kwee", "pee", "peea-wee", "peet-see", "tee-ho", "tee-whee", "tee-you", "teee-ur", "tew", "tew-whee", "towhee", "tseet", "twee", "tweet", "wheep", "wreet", "zweet"], "Chirps": ["a-a", "a-oh", "che-wink", "chi-chi", "chip", "chirrup", "chuh", "chuhli", "dri-drop", "ikka-chi", "kidick", "piri-piro", "trill", "wheeo-chchi", "whit-whit", "wikwik"], "Hoots": ["hoo", "hooho", "hoohooo", "hooroo", "hoot", "hru", "koo-ah", "koo-koo", "mwah", "pwah", "ruru", "tiroo", "too-loo", "toowit", "tuwu", "twoah", "twoo", "whill", "whipoor", "whoo", "whoo-ah"]}, "Fish": {"Fish": ["bilp", "blib", "blip", "bloolgh", "blub", "blup", "boolp", "dilp", "dool", "floop", "ghool", "gloogh", "glob", "glop", "glub", "gluup", "googh", "guulgh", "ool", "plop", "polgh", "poolp", "quilp", "quolp", "sblop", "shib", "shup", "thilp", "thlup", "thoop"], "Sharks": ["arllg", "aurch", "ferllch", "frach", "fragh", "frauch", "frrechk", "grach", "grallch", "grech", "grellch", "gruch", "grullch", "kaurch", "rauch", "rechk", "shkurr", "shralk", "shregk", "shrrukk"], "Eels": ["lool", "mool", "ooz", "silv", "slee", "sleem", "sleez", "sliv", "sliz", "sloov", "smee", "sneel", "snilv", "snool", "sool", "szee", "szoo", "veez", "vlee", "vliz", "vloo", "vool", "voolm", "vooz", "zeev", "zilv", "zliv", "zloo", "zool", "zoov"]}, "Reptiles": {"Turtles": ["haash", "heem", "ihxaan", "inixh", "kahxtu", "kam", "kiul", "mahz", "mierz", "mursh", "reehm", "scux", "shai", "shar", "sheel", "siul", "skeen", "slaxas", "strai", "suliz", "sxur", "taish", "tur", "tzenx", "tzesh", "tzuhan", "tzur", "xeem", "xhan", "xurelz"], "Lizards": ["ahsk", "anakh", "ikhsar", "inkh", "isith", "izkur", "kar", "kisz", "krah", "krizil", "lirisk", "liszth", "rah", "rahk", "rahn", "rahst", "rahz", "rausz", "salar", "sar", "sard", "sarn", "skurr", "skih", "slith", "sliz", "surt", "szaur", "zahsu", "zar", "zark", "zilakh"], "Snakes": ["aassp", "hish", "hisstah", "issah", "issh", "kaa", "kepesh", "nepthiss", "ness", "nissp", "peshep", "shaash", "shaah", "shaass", "shissk", "ssaan", "ssaath", "ssaah", "ssashen", "ssep", "sseth", "ssin", "ssipth", "ssnaah", "ssnepth", "vaass", "vaathiss", "viss", "vissp", "yaash", "yiss"]}, "Amphibians": {"Frogs": ["bhirr", "bhurr", "bi-bugh", "braarp", "breek", "brekk", "brepp", "brib", "bripp", "broo\u00e4kk", "brrarp", "bruurk", "bulph", "kek-kek", "khroap", "ko\u00e4rk", "ko\u00e4x", "krekkek", "phe\u00e4rp", "pribbit", "phrip-pip", "ribbit"], "Toads": ["boag", "bolg", "brolg", "gaarlb", "goag", "goalb", "golg", "goln", "graal", "roalb", "roalg", "rolg", "rolv", "slaag", "slaan", "slaar", "slaav", "sloag", "slorg", "slorv", "soag", "vaarg", "vlaar", "vlaaz", "voag", "volg", "vraag", "vraal", "vrog", "vrol"]}}